numericalunits.py
numericalunits-1.26.dist-info/LICENSE.txt
numericalunits-1.26.dist-info/METADATA
numericalunits-1.26.dist-info/WHEEL
numericalunits-1.26.dist-info/top_level.txt
numericalunits-1.26.dist-info/RECORD
