Metadata-Version: 2.1
Name: numericalunits
Version: 1.26
Summary: A package that lets you define quantities with units, which can then be used in almost any numerical calculation in any programming language. Checks that calculations pass dimensional analysis, performs unit conversions, and defines physical constants.
Author-email: Steven Byrnes <steven.byrnes@gmail.com>
License: MIT
Project-URL: Homepage, http://pypi.python.org/pypi/numericalunits
Project-URL: Repository, https://github.com/sbyrnes321/numericalunits
Keywords: units, quantities, physical constants, dimensional analysis
Classifier: Development Status :: 5 - Production/Stable
Classifier: Intended Audience :: Science/Research
Classifier: Topic :: Scientific/Engineering
Classifier: License :: OSI Approved :: MIT License
Classifier: Operating System :: OS Independent
Classifier: Programming Language :: Python :: 3
Requires-Python: >=3
License-File: LICENSE.txt
